vaknl_gcp/__init__.py
vaknl_gcp/Bigquery/__init__.py
vaknl_gcp/DataClasses/__init__.py
vaknl_gcp/Scheduler/AppEngine.py
vaknl_gcp/Scheduler/HTTP.py
vaknl_gcp/Scheduler/PubSub.py
vaknl_gcp/Scheduler/Schedule.py
vaknl_gcp/Scheduler/__init__.py
vaknl_gcp/Scheduler/test.py
vaknl_gcp/Secrets/__init__.py
vaknl_gcp/Storage/__init__.py
vaknl_gcp/Tasks/__init__.py
vaknl_gcp-1.3.7.dist-info/LICENSE
vaknl_gcp-1.3.7.dist-info/METADATA
vaknl_gcp-1.3.7.dist-info/WHEEL
vaknl_gcp-1.3.7.dist-info/top_level.txt
vaknl_gcp-1.3.7.dist-info/RECORD
