Metadata-Version: 2.1
Name: vaknl-gcp
Version: 1.3.7
Summary: Vakanties.nl pypi package
Home-page: https://github.com/vakantiesnl/vaknl-PyPi.git
Author: Wytze Bruinsma
Author-email: wytze.bruinsma@vakanties.nl
License: UNKNOWN
Keywords: vaknl,pip
Platform: UNKNOWN
Requires-Python: >=3.7
License-File: LICENSE
Requires-Dist: google-cloud-bigquery (==1.28.0)
Requires-Dist: google-cloud-storage (==1.31.1)
Requires-Dist: google-cloud-secret-manager (==1.0.0)
Requires-Dist: newlinejson
Requires-Dist: google-cloud-tasks (==1.3.0)
Requires-Dist: googleapis-common-protos (==1.6.0)
Requires-Dist: google-cloud-scheduler (==1.3.0)
Requires-Dist: croniter
